erpn/__init__.py
erpn/__main__.py
erpn/buttonMappings.py
erpn/cursesHelper.py
erpn/domain.py
erpn/functions.py
erpn/main.py
erpn/stackFormat.py
erpn/urwidHelper.py
erpn/urwidInterface.py
erpn-1.0.dist-info/DESCRIPTION.rst
erpn-1.0.dist-info/METADATA
erpn-1.0.dist-info/RECORD
erpn-1.0.dist-info/WHEEL
erpn-1.0.dist-info/entry_points.txt
erpn-1.0.dist-info/metadata.json
erpn-1.0.dist-info/top_level.txt
