Metadata-Version: 2.0
Name: erpn
Version: 1.0
Summary: An RPN Calculator
Home-page: http://github.com/BartDeWaal/ERPN
Author: Bart de Waal
Author-email: bart@tuduft.nl
License: GPLv3
Keywords: rpn
Platform: UNKNOWN
Classifier: Development Status :: 5 - Production/Stable
Classifier: Environment :: Console
Classifier: Intended Audience :: Science/Research
Classifier: License :: OSI Approved :: GNU General Public License v3 (GPLv3)
Classifier: Natural Language :: English
Classifier: Programming Language :: Python :: 3
Classifier: Topic :: Scientific/Engineering :: Mathematics
Classifier: Topic :: Utilities
Classifier: Operating System :: POSIX
Requires-Dist: pyperclip
Requires-Dist: urwid
